ingreedypy.py
ingreedypy-1.3.8.dist-info/LICENSE
ingreedypy-1.3.8.dist-info/METADATA
ingreedypy-1.3.8.dist-info/WHEEL
ingreedypy-1.3.8.dist-info/top_level.txt
ingreedypy-1.3.8.dist-info/RECORD
