Metadata-Version: 2.1
Name: ingreedypy
Version: 1.3.8
Summary: ingreedy-py parses recipe ingredient lines into a object
Home-page: https://github.com/openculinary/ingreedy-py
Author: Scott Cooper
Author-email: scttcper@gmail.com
Keywords: ingreedy,ingreedypy,recipe,parser
Classifier: License :: OSI Approved :: MIT License
Classifier: Operating System :: OS Independent
License-File: LICENSE
Requires-Dist: parsimonious
Provides-Extra: tests
Requires-Dist: pytest ; extra == 'tests'
Requires-Dist: pytest-cov ; extra == 'tests'
